cantocut/__init__.py
cantocut/vocab/cmn.vocab
cantocut/vocab/yue.vocab
cantocut-0.0.2.dist-info/METADATA
cantocut-0.0.2.dist-info/WHEEL
cantocut-0.0.2.dist-info/top_level.txt
cantocut-0.0.2.dist-info/RECORD
