Metadata-Version: 2.1
Name: cantocut
Version: 0.0.2
Summary: word segmentation for cantonese
Home-page: https://github.com/machow/cantocut
Author: Michael Chow
Author-email: mc_al_cantocut@fastmail.com
License: UNKNOWN
Platform: UNKNOWN
Requires-Dist: astar
